systembridgegui/__init__.py
systembridgegui/__main__.py
systembridgegui/_version.py
systembridgegui/icon.png
systembridgegui/system_tray.py
systembridgegui/widgets/__init__.py
systembridgegui/widgets/timed_message_box.py
systembridgegui/window/__init__.py
systembridgegui/window/main.py
systembridgegui/window/notification.py
systembridgegui/window/player.py
systembridgegui-4.0.4.dist-info/LICENSE
systembridgegui-4.0.4.dist-info/METADATA
systembridgegui-4.0.4.dist-info/WHEEL
systembridgegui-4.0.4.dist-info/top_level.txt
systembridgegui-4.0.4.dist-info/RECORD
